{
  "schema_version": "3.0.0",
  "task_id": "dr_cross_v3_0108",
  "sites": [
    "shopping"
  ],
  "intent": "Find ONE noise-cancelling headphone listed on the One Stop Market shopping site under $50. Write a 200-word mini-review with (a) exact product name, (b) price, (c) rating, (d) one sentence of what buyers praise, (e) one sentence of the main complaint. Cite the product URL. No Reddit, no Wikipedia.",
  "start_url": "__SHOPPING__/electronics.html",
  "storage_state": null,
  "require_login": false,
  "markdown_spec": {
    "min_words": 180,
    "max_words": 400,
    "min_paragraphs": 3,
    "min_citations": 1,
    "min_pages_browsed": 2
  },
  "citation_policy": {
    "required_for": [],
    "must_be_in_domain": [
      "__SHOPPING__"
    ],
    "min_distinct_sources": 1
  },
  "golden": {
    "triples_path": "data/golden/dr_cross_v3_0108.json",
    "expected_predicates": [
      "price",
      "rating",
      "product_url"
    ]
  },
  "coverage_checklist_path": "data/tasks/deep_research/cross_site/checklists_v3.json",
  "difficulty": 2,
  "expected_steps": 5,
  "author_notes": "Smoke. Single-site, 5-min regression check.",
  "tier": "smoke"
}